{
	"$schema": "http://schema.management.azure.com/schemas/2015-01-01/deploymentTemplate.json#",
	"contentVersion": "1.0.0.0",
	"parameters": {
		"factoryName": {
			"type": "string",
			"metadata": "Data Factory name",
			"defaultValue": "ADF-Practice-DKM"
		},
		"ADLS_LS_accountKey": {
			"type": "secureString",
			"metadata": "Secure string for 'accountKey' of 'ADLS_LS'"
		},
		"Azure_SqlDB_LS_password": {
			"type": "secureString",
			"metadata": "Secure string for 'password' of 'Azure_SqlDB_LS'"
		},
		"ADLS_LS_properties_typeProperties_url": {
			"type": "string",
			"defaultValue": "https://adls5synapse.dfs.core.windows.net/"
		},
		"Azure_SqlDB_LS_properties_typeProperties_server": {
			"type": "string",
			"defaultValue": "sqlserverforsqldb.database.windows.net"
		},
		"Azure_SqlDB_LS_properties_typeProperties_database": {
			"type": "string",
			"defaultValue": "sql_db"
		},
		"Azure_SqlDB_LS_properties_typeProperties_userName": {
			"type": "string",
			"defaultValue": "dkm"
		}
	},
	"variables": {
		"factoryId": "[concat('Microsoft.DataFactory/factories/', parameters('factoryName'))]"
	},
	"resources": [
		{
			"name": "[concat(parameters('factoryName'), '/pipeline1')]",
			"type": "Microsoft.DataFactory/factories/pipelines",
			"apiVersion": "2018-06-01",
			"properties": {
				"activities": [
					{
						"name": "Copy Orders Data",
						"type": "Copy",
						"dependsOn": [],
						"policy": {
							"timeout": "0.12:00:00",
							"retry": 0,
							"retryIntervalInSeconds": 30,
							"secureOutput": false,
							"secureInput": false
						},
						"userProperties": [],
						"typeProperties": {
							"source": {
								"type": "AzureSqlSource",
								"queryTimeout": "02:00:00",
								"partitionOption": "None"
							},
							"sink": {
								"type": "JsonSink",
								"storeSettings": {
									"type": "AzureBlobFSWriteSettings"
								},
								"formatSettings": {
									"type": "JsonWriteSettings"
								}
							},
							"enableStaging": false
						},
						"inputs": [
							{
								"referenceName": "AzureSqlTable1",
								"type": "DatasetReference",
								"parameters": {}
							}
						],
						"outputs": [
							{
								"referenceName": "Orders",
								"type": "DatasetReference",
								"parameters": {}
							}
						]
					}
				],
				"policy": {
					"elapsedTimeMetric": {}
				},
				"annotations": []
			},
			"dependsOn": [
				"[concat(variables('factoryId'), '/datasets/AzureSqlTable1')]",
				"[concat(variables('factoryId'), '/datasets/Orders')]"
			]
		},
		{
			"name": "[concat(parameters('factoryName'), '/AzureSqlTable1')]",
			"type": "Microsoft.DataFactory/factories/datasets",
			"apiVersion": "2018-06-01",
			"properties": {
				"linkedServiceName": {
					"referenceName": "Azure_SqlDB_LS",
					"type": "LinkedServiceReference"
				},
				"annotations": [],
				"type": "AzureSqlTable",
				"schema": [
					{
						"name": "SalesOrderID",
						"type": "int",
						"precision": 10
					},
					{
						"name": "SalesOrderDetailID",
						"type": "int",
						"precision": 10
					},
					{
						"name": "OrderQty",
						"type": "smallint",
						"precision": 5
					},
					{
						"name": "ProductID",
						"type": "int",
						"precision": 10
					},
					{
						"name": "UnitPrice",
						"type": "money",
						"precision": 19,
						"scale": 4
					},
					{
						"name": "UnitPriceDiscount",
						"type": "money",
						"precision": 19,
						"scale": 4
					},
					{
						"name": "LineTotal",
						"type": "decimal",
						"precision": 38,
						"scale": 6
					},
					{
						"name": "rowguid",
						"type": "uniqueidentifier"
					},
					{
						"name": "ModifiedDate",
						"type": "datetime",
						"precision": 23,
						"scale": 3
					}
				],
				"typeProperties": {
					"schema": "SalesLT",
					"table": "SalesOrderDetail"
				}
			},
			"dependsOn": [
				"[concat(variables('factoryId'), '/linkedServices/Azure_SqlDB_LS')]"
			]
		},
		{
			"name": "[concat(parameters('factoryName'), '/Orders')]",
			"type": "Microsoft.DataFactory/factories/datasets",
			"apiVersion": "2018-06-01",
			"properties": {
				"linkedServiceName": {
					"referenceName": "ADLS_LS",
					"type": "LinkedServiceReference"
				},
				"annotations": [],
				"type": "Json",
				"typeProperties": {
					"location": {
						"type": "AzureBlobFSLocation",
						"folderPath": "Json",
						"fileSystem": "landing"
					}
				},
				"schema": {}
			},
			"dependsOn": [
				"[concat(variables('factoryId'), '/linkedServices/ADLS_LS')]"
			]
		},
		{
			"name": "[concat(parameters('factoryName'), '/ADLS_LS')]",
			"type": "Microsoft.DataFactory/factories/linkedServices",
			"apiVersion": "2018-06-01",
			"properties": {
				"annotations": [],
				"type": "AzureBlobFS",
				"typeProperties": {
					"url": "[parameters('ADLS_LS_properties_typeProperties_url')]",
					"accountKey": {
						"type": "SecureString",
						"value": "[parameters('ADLS_LS_accountKey')]"
					}
				}
			},
			"dependsOn": []
		},
		{
			"name": "[concat(parameters('factoryName'), '/Azure_SqlDB_LS')]",
			"type": "Microsoft.DataFactory/factories/linkedServices",
			"apiVersion": "2018-06-01",
			"properties": {
				"annotations": [],
				"type": "AzureSqlDatabase",
				"typeProperties": {
					"server": "[parameters('Azure_SqlDB_LS_properties_typeProperties_server')]",
					"database": "[parameters('Azure_SqlDB_LS_properties_typeProperties_database')]",
					"encrypt": "mandatory",
					"trustServerCertificate": false,
					"authenticationType": "SQL",
					"userName": "[parameters('Azure_SqlDB_LS_properties_typeProperties_userName')]",
					"password": {
						"type": "SecureString",
						"value": "[parameters('Azure_SqlDB_LS_password')]"
					}
				}
			},
			"dependsOn": []
		}
	]
}